sstf/__init__.py
sstf/__main__.py
sstf-0.0.2.dist-info/LICENSE
sstf-0.0.2.dist-info/METADATA
sstf-0.0.2.dist-info/WHEEL
sstf-0.0.2.dist-info/entry_points.txt
sstf-0.0.2.dist-info/top_level.txt
sstf-0.0.2.dist-info/RECORD
