Metadata-Version: 2.1
Name: sstf
Version: 0.0.2
Author: lxhzzy
Author-email: lxhzzy@outlook.com
License: MIT
License-File: LICENSE
Requires-Dist: psutil
Requires-Dist: argparse
Requires-Dist: pathlib
